[{"question":"1. What two characteristics describe an FTP connection? (Choose two.)","answers":[{"answer":"The first connection established is for traffic control and the second connection is created to transfer a file."},{"answer":"Files can be downloaded from or uploaded to the server."}]},{"question":"2. Refer to the exhibit. Consider the IP address configuration shown from PC1. What is a description of the default gateway address?","answers":[{"answer":"It is the IP address of the Router1 interface that connects the PC1 LAN to Router1."},{"answer":"3. Open the PT activity. Perform the tasks in the activity instructions and then answer the question."}]},{"question":"What is the application layer service being requested from Server0 by PC0?","answers":[]},{"question":"In the Simulation mode, capture the packets. What is the application layer service being requested from Server0 by PC0?\nReturn to the assessment to answer the question.","answers":[{"answer":"HTTPS"}]},{"question":"4. Which statement describes the physical topology for a LAN?","answers":[{"answer":"It defines how hosts and network devices connect to the LAN."},{"answer":"5. Match the term to the value represented."}]}]